{
  "$schema": "http://json-schema.org/schema#",
  "self": {
    "vendor": "com.nordstrom",
    "name": "retail-stream-egress",
    "format": "jsonschema",
    "version": "1-0-0"
  },
  "type": "object",
  "properties": {
    "schema":      { "type": "string" },
    "followsFrom": { "type": "string" },
    "origin":      { "type": "string" },
    "timeOrigin":  { "type": "string", "format": "date-time" },
    "data": {
      "type": "object",
      "properties": {
        "schema": { "type": "string" }
      },
      "required": [
        "schema"
      ],
      "additionalProperties": true
    },
    "eventId": { "type": "string" },
    "timeIngest":  { "type": "string", "format": "date-time" },
    "timeProcess": { "type": "string", "format": "date-time" }
  },
  "required": [
    "schema",
    "origin",
    "timeOrigin",
    "data",
    "eventId",
    "timeIngest",
    "timeProcess"
  ],
  "additionalProperties": false
}
